thunderdome
