Metadata-Version: 1.0
Name: thunderdome
Version: 0.4.6
Summary: Titan Object-Graph Mapper (OGM)
Home-page: https://github.com/StartTheShift/thunderdome
Author: StartTheShift
Author-email: dev@shift.com
License: BSD
Keywords: cassandra,titan,ogm,thunderdome
Platform: UNKNOWN
Classifier: Development Status :: 3 - Alpha
Classifier: Environment :: Web Environment
Classifier: Environment :: Plugins
Classifier: License :: OSI Approved :: BSD License
Classifier: Operating System :: OS Independent
Classifier: Programming Language :: Python :: 2.6
Classifier: Programming Language :: Python :: 2.7
Classifier: Topic :: Internet :: WWW/HTTP
Classifier: Topic :: Software Development :: Libraries :: Python Modules
